{
  "locations": [
    {
      "loc_name": "Site Gallery",
      "loc_lat": 53.376653,
      "loc_long": -1.466140,
      "events":["mountain-pastures.mp3"]
    },
    {
      "loc_name": "Playground Charles St",
      "loc_lat": 53.377175,
      "loc_long": -1.466566,
      "events":["Grasshoppers.mp3"]
    },
    {
      "loc_name": "Sheffield Station",
      "loc_lat": 53.378258,
      "loc_long": -1.463221,
      "events":[]
    },
	  {
      "loc_name": "Peace Gardens",
      "loc_lat": 53.379973,
      "loc_long": -1.469406,
      "events":[]
    },
    {
      "loc_name": "Millennium Art Gallery",
      "loc_lat": 53.380183,
      "loc_long": -1.467754,
      "events":[]
    },
	{
	"loc_name": "Hallam Square",
      "loc_lat": 53.378972, 
      "loc_long": -1.466415,
      "events":["Sea.mp3"]
	}
  ]
}